scraper/__init__.py
scraper/scraper.py
pa_scraper-0.2.4.dist-info/LICENCE
pa_scraper-0.2.4.dist-info/METADATA
pa_scraper-0.2.4.dist-info/WHEEL
pa_scraper-0.2.4.dist-info/top_level.txt
pa_scraper-0.2.4.dist-info/RECORD
