Metadata-Version: 2.1
Name: pa-scraper
Version: 0.2.4
Summary: Python wrapper for Prompt API's Scraper API
Home-page: https://github.com/promptapi/scraper-py
Author: Prompt API
Author-email: hello@promptapi.com
License: MIT
Project-URL: Prompt API, https://promptapi.com
Project-URL: Scraper API, https://promptapi.com/marketplace/description/scraper-api
Project-URL: Source, https://github.com/promptapi/scraper-py
Keywords: promptapi,scrape,extract,parse,download
Platform: UNKNOWN
Classifier: Development Status :: 4 - Beta
Classifier: License :: OSI Approved :: MIT License
Classifier: Operating System :: OS Independent
Classifier: Programming Language :: Python :: 3
Classifier: Programming Language :: Python :: 3.7
Classifier: Programming Language :: Python :: 3 :: Only
Classifier: Intended Audience :: Developers
Classifier: Intended Audience :: Information Technology
Classifier: Topic :: Software Development :: Libraries :: Python Modules
Classifier: Topic :: Internet :: WWW/HTTP :: Indexing/Search
Classifier: Topic :: Text Processing :: General
Requires-Python: >=3.7
Requires-Dist: requests
Provides-Extra: development
Requires-Dist: vb-console ; extra == 'development'
